LICENSE
MANIFEST.in
README.md
setup.py
uricore/__init__.py
uricore/core.py
uricore/template.py
uricore/wkz_datastructures.py
uricore/wkz_internal.py
uricore/wkz_urls.py
uricore/wkz_wsgi.py
uricore.egg-info/PKG-INFO
uricore.egg-info/SOURCES.txt
uricore.egg-info/dependency_links.txt
uricore.egg-info/top_level.txt