Metadata-Version: 1.0
Name: uricore
Version: 0.1.2
Summary: URI Parsing for Humans.
Home-page: https://github.com/core/uricore
Author: Matthew Hooker & Jeremy Avnet & Matt Chisholm
Author-email: uricore@librelist.com
License: BSD
Platform: UNKNOWN
Classifier: Development Status :: 4 - Beta
Classifier: Intended Audience :: Developers
Classifier: Natural Language :: English
Classifier: License :: OSI Approved :: BSD License
Classifier: Programming Language :: Python
Classifier: Programming Language :: Python :: 2.6
Classifier: Programming Language :: Python :: 2.7
